mcpwrap-0.1.0.dist-info/licenses/LICENSE
simplemcp/__init__.py
simplemcp/simplemcp.py
mcpwrap-0.1.0.dist-info/METADATA
mcpwrap-0.1.0.dist-info/WHEEL
mcpwrap-0.1.0.dist-info/top_level.txt
mcpwrap-0.1.0.dist-info/RECORD
